lbfgsb/__about__.py
lbfgsb/__init__.py
lbfgsb/_numba_helpers.py
lbfgsb/base.py
lbfgsb/benchmarks.py
lbfgsb/bfgsmats.py
lbfgsb/cauchy.py
lbfgsb/linesearch.py
lbfgsb/main.py
lbfgsb/scalar_function.py
lbfgsb/subspacemin.py
lbfgsb/types.py
lbfgsb/utils.py
lbfgsb-1.0.0.dist-info/AUTHORS.rst
lbfgsb-1.0.0.dist-info/LICENSE
lbfgsb-1.0.0.dist-info/METADATA
lbfgsb-1.0.0.dist-info/WHEEL
lbfgsb-1.0.0.dist-info/top_level.txt
lbfgsb-1.0.0.dist-info/RECORD
