Metadata-Version: 2.2
Name: lbfgsb
Version: 1.0.0
Summary: A python impementation of the famous L-BFGS-B quasi-Newton solver.
Author-email: Antoine Collet <antoinecollet5@gmail.com>
License: BSD 3-Clause License
Project-URL: Homepage, https://pypi.org/project/lbfgsb/
Project-URL: Documentation, https://lbfgsb.readthedocs.io/en/latest/
Project-URL: Repository, https://github.com/antoinecollet5/lbfgsb
Project-URL: Issues, https://github.com/antoinecollet5/lbfgsb/issues
Project-URL: Changelog, https://github.com/antoinecollet5/lbfgsb/blob/master/CHANGELOG.rst
Keywords: Limited,Bounded,Minimization,Gradient descent,Quasi-Newton,Parameters estimation,L-BFGS-B
Classifier: Development Status :: 5 - Production/Stable
Classifier: Intended Audience :: Developers
Classifier: Natural Language :: English
Classifier: Programming Language :: Python :: 3
Classifier: Programming Language :: Python :: 3.7
Classifier: Programming Language :: Python :: 3.8
Classifier: Programming Language :: Python :: 3.9
Classifier: Programming Language :: Python :: 3.10
Classifier: Programming Language :: Python :: 3.11
Classifier: Programming Language :: Python :: 3.12
Classifier: Programming Language :: Python :: 3.13
Classifier: Programming Language :: Python :: 3.14
Requires-Python: >=3.7
License-File: LICENSE
License-File: AUTHORS.rst
Requires-Dist: setuptools
Requires-Dist: wheel
Requires-Dist: numpy>=1.2
Requires-Dist: scipy>=1.6.2
Requires-Dist: packaging; python_version < "3.8"
Requires-Dist: typing_extensions; python_version < "3.8"
Provides-Extra: all
Requires-Dist: lbfgsb[docs,examples,install,lint,numba,tests]; extra == "all"
Provides-Extra: numba
Requires-Dist: numba; extra == "numba"
Provides-Extra: docs
Requires-Dist: sphinx<9; extra == "docs"
Requires-Dist: nbsphinx; extra == "docs"
Requires-Dist: nbsphinx-link>=1.3.1; extra == "docs"
Requires-Dist: jupyter_sphinx>=0.3.2; extra == "docs"
Requires-Dist: sphinx-jsonschema>=1.15; extra == "docs"
Requires-Dist: pygments>=2.11.1; extra == "docs"
Requires-Dist: pydata-sphinx-theme; extra == "docs"
Requires-Dist: sphinxcontrib-bibtex; extra == "docs"
Provides-Extra: tests
Requires-Dist: twine==1.14.0; extra == "tests"
Requires-Dist: pytest; extra == "tests"
Requires-Dist: pytest-runner; extra == "tests"
Requires-Dist: pytest-cov; extra == "tests"
Requires-Dist: pytest-cookies; extra == "tests"
Requires-Dist: coverage; extra == "tests"
Requires-Dist: numdifftools; extra == "tests"
Provides-Extra: examples
Requires-Dist: matplotlib; extra == "examples"
Provides-Extra: lint
Requires-Dist: pre-commit; extra == "lint"
Requires-Dist: codespell>=2.1.0; extra == "lint"
Requires-Dist: ruff; extra == "lint"
Requires-Dist: ty; python_version > "3.7" and extra == "lint"
Provides-Extra: install
Requires-Dist: pip; extra == "install"
Requires-Dist: wheel; extra == "install"
